{"meta": {"sha": "76d160d423366cc27d3bdf3274bb68ff458185ed", "short": "76d160d", "platform": "linux", "repo": "sganjoo/Arrays-Demo", "pages_url": "https://sganjoo.github.io/Arrays-Demo", "snap_base": "https://sganjoo.github.io/Arrays-Demo/vi-snapshots/", "dash_url": "https://sganjoo.github.io/Arrays-Demo/", "labview_version": "2026", "commit": {"message": "Merge pull request #2 from sganjoo/UploadLVCode", "author": "sganjoo", "date": "2018-05-14T16:13:21-05:00"}, "generated_utc": "2026-06-22 21:07 UTC"}, "summary": {"total": 5, "ok": 5, "bad": 0, "percent": 100, "status": "partial", "exit": 3, "duration": 14, "missing_deps": 2, "problem_vis": 2}, "categories": {"broken": {"label": "Failed to compile", "color": "#da3633", "blurb": "LabVIEW flagged the VI as bad — it could not load or compile here"}, "dependency": {"label": "Missing dependency", "color": "#bb8009", "blurb": "A subVI / dependency could not be found in this container"}}, "category_order": ["broken", "dependency"], "platforms": [{"id": "windows", "url": "../problems.json"}, {"id": "linux", "url": null}], "vis": [{"name": "VI to XML.vi", "vi_rel": "", "group": "Unresolved", "problems": [{"type": "Missing dependency", "severity": "dependency", "message": "Could not find subVI \"LV AI Core.lvlib:XML generator.vi\" (last known at /workspace/.github/labview/toimages/_ni/labview/lvctl/vis/LV AI Core/XML generator.vi)."}], "total": 1, "sev_counts": {"broken": 0, "dependency": 1}, "resolved": false}, {"name": "XML to VI.vi", "vi_rel": "", "group": "Unresolved", "problems": [{"type": "Missing dependency", "severity": "dependency", "message": "Could not find subVI \"LV AI Core.lvlib:VI generator.vi\" (last known at /workspace/.github/labview/toimages/_ni/labview/lvctl/vis/LV AI Core/VI generator.vi)."}], "total": 1, "sev_counts": {"broken": 0, "dependency": 1}, "resolved": false}]}